concat_stories/__init__.py
concat_stories/app.py
concat_stories/con_stories.py
concat_stories/snapchat_dl.py
concat_stories-0.4.2.dist-info/METADATA
concat_stories-0.4.2.dist-info/WHEEL
concat_stories-0.4.2.dist-info/entry_points.txt
concat_stories-0.4.2.dist-info/top_level.txt
concat_stories-0.4.2.dist-info/RECORD
