Metadata-Version: 2.4
Name: concat-stories
Version: 0.4.2
Summary: Concatenate Snapchat stories.
Author-email: Ayoub Dya <ayoubdya@gmail.com>
License: MIT
Project-URL: Homepage, https://github.com/ayoubdya/concat-stories
Keywords: concat-stories,snapchat,stories,video,concatenate
Classifier: Development Status :: 3 - Alpha
Classifier: Intended Audience :: Developers
Classifier: License :: OSI Approved :: MIT License
Requires-Python: >=3.8
Requires-Dist: loguru
Requires-Dist: requests
Requires-Dist: ffmpeg-python
